st_text_component/__init__.py
st_text_component/example.py
st_text_component/streamlit_callback.py
st_text_component/frontend/build/asset-manifest.json
st_text_component/frontend/build/bootstrap.min.css
st_text_component/frontend/build/index.html
st_text_component/frontend/build/static/css/main.1fd74231.css
st_text_component/frontend/build/static/css/main.1fd74231.css.map
st_text_component/frontend/build/static/js/main.72debba1.js
st_text_component/frontend/build/static/js/main.72debba1.js.LICENSE.txt
st_text_component/frontend/build/static/js/main.72debba1.js.map
streamlit_text_component-0.0.7.dist-info/LICENSE
streamlit_text_component-0.0.7.dist-info/METADATA
streamlit_text_component-0.0.7.dist-info/WHEEL
streamlit_text_component-0.0.7.dist-info/top_level.txt
streamlit_text_component-0.0.7.dist-info/RECORD
